Metadata-Version: 1.0
Name: mosaiq-connection
Version: 0.2.0
Summary: A toolbox for interacting with Mosaiq SQL.
Home-page: UNKNOWN
Author: Simon Biggs
Author-email: mail@simonbiggs.net
License: AGPL3+
Platform: UNKNOWN
